_pywhispercpp.cpython-314-aarch64-linux-gnu.so
libggml-base.so
libggml-cpu.so
libggml.so
libwhisper.so
libwhisper.so.1
libwhisper.so.1.8.2
pywhispercpp/__init__.py
pywhispercpp/constants.py
pywhispercpp/model.py
pywhispercpp/utils.py
pywhispercpp/examples/__init__.py
pywhispercpp/examples/assistant.py
pywhispercpp/examples/gui.py
pywhispercpp/examples/livestream.py
pywhispercpp/examples/main.py
pywhispercpp/examples/recording.py
pywhispercpp.libs/libggml-7cd3dc39.so
pywhispercpp.libs/libggml-base-aa65cefd.so
pywhispercpp.libs/libggml-cpu-19d5f6f7.so
pywhispercpp.libs/libgomp-a49a47f9.so.1.0.0
pywhispercpp.libs/libwhisper-5781fb12.so.1.8.2
pywhispercpp-1.4.1.dist-info/METADATA
pywhispercpp-1.4.1.dist-info/WHEEL
pywhispercpp-1.4.1.dist-info/entry_points.txt
pywhispercpp-1.4.1.dist-info/top_level.txt
pywhispercpp-1.4.1.dist-info/RECORD
pywhispercpp-1.4.1.dist-info/licenses/LICENSE
pywhispercpp-1.4.1.dist-info/sboms/auditwheel.cdx.json
