Metadata-Version: 2.4
Name: pywhispercpp
Version: 1.4.1
Summary: Python bindings for whisper.cpp
Author: absadiki
License: MIT
Project-URL: Documentation, https://absadiki.github.io/pywhispercpp/
Project-URL: Source, https://github.com/absadiki/pywhispercpp
Project-URL: Tracker, https://github.com/absadiki/pywhispercpp/issues
Requires-Python: >=3.8
License-File: LICENSE
Requires-Dist: numpy
Requires-Dist: requests
Requires-Dist: tqdm
Requires-Dist: platformdirs
Provides-Extra: examples
Requires-Dist: sounddevice; extra == "examples"
Requires-Dist: webrtcvad; extra == "examples"
Provides-Extra: gui
Requires-Dist: pyqt5; extra == "gui"
Dynamic: author
Dynamic: description
Dynamic: description-content-type
Dynamic: license
Dynamic: license-file
Dynamic: project-url
Dynamic: provides-extra
Dynamic: requires-dist
Dynamic: requires-python
Dynamic: summary
